trimap/BERT.py
trimap/__init__.py
trimap/model.py
trimap/net.py
trimap/utils.py
trimap_tools-1.0.5.dist-info/licenses/LICENSE
trimap_tools-1.0.5.dist-info/METADATA
trimap_tools-1.0.5.dist-info/WHEEL
trimap_tools-1.0.5.dist-info/top_level.txt
trimap_tools-1.0.5.dist-info/RECORD
