Metadata-Version: 2.4
Name: trimap-tools
Version: 1.0.5
Summary: Discovering TCR-Epitope-HLA interactions with Deep Learning
Home-page: https://github.com/uhler/trimap-tools
Author: Kai Cao
Author-email: caokai1073@gmail.com
Classifier: Programming Language :: Python :: 3
Classifier: Programming Language :: Python :: 3.9
Classifier: Programming Language :: Python :: 3.10
Classifier: Programming Language :: Python :: 3.11
Classifier: License :: OSI Approved :: MIT License
Classifier: Operating System :: OS Independent
Requires-Python: >=3.9
License-File: LICENSE
Requires-Dist: numpy
Requires-Dist: pandas
Requires-Dist: torch
Requires-Dist: scikit-learn
Requires-Dist: tqdm
Requires-Dist: transformers
Requires-Dist: matplotlib
Requires-Dist: SentencePiece
Requires-Dist: seaborn
Dynamic: author
Dynamic: author-email
Dynamic: classifier
Dynamic: description
Dynamic: description-content-type
Dynamic: home-page
Dynamic: license-file
Dynamic: requires-dist
Dynamic: requires-python
Dynamic: summary
